loggerric/__init__.py
loggerric/_log.py
loggerric/_log_to_file.py
loggerric/_progress_bar.py
loggerric/_prompt.py
loggerric/_timer.py
loggerric/_timestamp.py
loggerric-1.5.6.dist-info/licenses/LICENSE
loggerric-1.5.6.dist-info/METADATA
loggerric-1.5.6.dist-info/WHEEL
loggerric-1.5.6.dist-info/top_level.txt
loggerric-1.5.6.dist-info/RECORD
