Metadata-Version: 2.4
Name: loggerric
Version: 1.5.6
Summary: A logging utility for Python. Developed for personal use.
Author: Luka Jacobsen
License: Creative Commons Attribution-NonCommercial 4.0 International (CC BY-NC 4.0)
Requires-Python: >=3.10
License-File: LICENSE
Dynamic: license-file
